pyttm/__init__.py
pyttm/app.py
pyttm/libs/__init__.py
pyttm/libs/crypto.py
pyttm/libs/db.py
pyttm/libs/helper.py
pyttm/libs/totp.py
pyttm-0.1.0.dist-info/LICENSE
pyttm-0.1.0.dist-info/METADATA
pyttm-0.1.0.dist-info/WHEEL
pyttm-0.1.0.dist-info/entry_points.txt
pyttm-0.1.0.dist-info/top_level.txt
pyttm-0.1.0.dist-info/RECORD
