Metadata-Version: 2.1
Name: pyttm
Version: 0.1.0
Summary: A simple Terminal based TOTP manager
Home-page: https://github.com/The-Robin-Hood/ttm
Author: The Robin Hood
License: MIT
Keywords: totp,otp,encryption,decryption,AES256,crypto,security,privacy
Platform: any
Classifier: Intended Audience :: Developers
Classifier: Topic :: Security
Classifier: Topic :: Utilities
Classifier: Development Status :: 4 - Beta
Classifier: Natural Language :: English
Classifier: License :: OSI Approved :: MIT License
Classifier: Operating System :: MacOS :: MacOS X
Classifier: Operating System :: Unix
Classifier: Operating System :: Microsoft :: Windows
Classifier: Programming Language :: Python :: 3
License-File: LICENSE
Requires-Dist: pycryptodome
